LICENSE
README.md
pyproject.toml
lazyslide/__init__.py
lazyslide/__main__.py
lazyslide/_api.py
lazyslide/_const.py
lazyslide/_setting.py
lazyslide/_utils.py
lazyslide/_version.py
lazyslide/py.typed
lazyslide/cv/__init__.py
lazyslide/cv/mask.py
lazyslide/cv/tiles_merger.py
lazyslide/cv/transform/__init__.py
lazyslide/cv/transform/compose.py
lazyslide/cv/transform/mods.py
lazyslide/datasets/__init__.py
lazyslide/datasets/_sample.py
lazyslide/io/__init__.py
lazyslide/io/_annotation.py
lazyslide/metrics/__init__.py
lazyslide/metrics/segmentation.py
lazyslide/metrics/topk.py
lazyslide/models/__init__.py
lazyslide/models/_model_registry.py
lazyslide/models/_repr.py
lazyslide/models/_utils.py
lazyslide/models/base.py
lazyslide/models/image_generation/__init__.py
lazyslide/models/image_generation/cytosyn.py
lazyslide/models/multimodal/__init__.py
lazyslide/models/multimodal/conch.py
lazyslide/models/multimodal/medsiglip.py
lazyslide/models/multimodal/musk.py
lazyslide/models/multimodal/omiclip.py
lazyslide/models/multimodal/plip.py
lazyslide/models/multimodal/prism.py
lazyslide/models/multimodal/titan.py
lazyslide/models/segmentation/__init__.py
lazyslide/models/segmentation/cellpose.py
lazyslide/models/segmentation/grandqc.py
lazyslide/models/segmentation/hest.py
lazyslide/models/segmentation/instanseg.py
lazyslide/models/segmentation/pathprofiler.py
lazyslide/models/segmentation/postprocess.py
lazyslide/models/segmentation/sam.py
lazyslide/models/segmentation/smp.py
lazyslide/models/segmentation/cellvit_family/__init__.py
lazyslide/models/segmentation/cellvit_family/histoplus.py
lazyslide/models/segmentation/cellvit_family/nulite.py
lazyslide/models/segmentation/cellvit_family/postprocess.py
lazyslide/models/segmentation/cellvit_family/blocks/__init__.py
lazyslide/models/segmentation/cellvit_family/blocks/modules.py
lazyslide/models/style_transfer/__init__.py
lazyslide/models/style_transfer/gigatime.py
lazyslide/models/style_transfer/rosie.py
lazyslide-0.10.0.dist-info/METADATA
lazyslide-0.10.0.dist-info/WHEEL
lazyslide-0.10.0.dist-info/entry_points.txt
lazyslide-0.10.0.dist-info/licenses/LICENSE
lazyslide-0.10.0.dist-info/RECORD
