Metadata-Version: 2.4
Name: lazyslide
Version: 0.10.0
Summary: Accessible and interoperable whole slide image analysis
Author-email: Yimin Zheng <yzheng@cemm.at>, Ernesto Abila <eabila@cemm.at>, "André F. Rendeiro" <arendeiro@cemm.at>
License-Expression: MIT
License-File: LICENSE
Keywords: deep learning,histopathology,image analysis,segmentation,whole slide image
Classifier: Development Status :: 3 - Alpha
Classifier: Intended Audience :: Science/Research
Classifier: License :: OSI Approved :: MIT License
Classifier: Natural Language :: English
Classifier: Operating System :: OS Independent
Classifier: Programming Language :: Python :: 3
Classifier: Topic :: File Formats
Classifier: Topic :: Scientific/Engineering :: Bio-Informatics
Requires-Python: >=3.11
Requires-Dist: cyclopts>=3.0.0
Requires-Dist: legendkit>=0.3.4
Requires-Dist: matplotlib-scalebar>=0.9.0
Requires-Dist: matplotlib>=3.9.0
Requires-Dist: psutil>=5.9.0
Requires-Dist: rich>=13.0.0
Requires-Dist: scikit-image>=0.23.1
Requires-Dist: scikit-learn>=1.0
Requires-Dist: seaborn>=0.12.2
Requires-Dist: timm>=1.0.3
Requires-Dist: torch>=2.0.0
Requires-Dist: wsidata>=0.7.0
Provides-Extra: all
Requires-Dist: scanpy>=1.10.4; extra == 'all'
Requires-Dist: scipy>=1.15.1; extra == 'all'
Requires-Dist: torchstain>=1.4.1; extra == 'all'
Requires-Dist: torchvision>=0.15; extra == 'all'
Requires-Dist: transformers>=4.49.0; extra == 'all'
Provides-Extra: models
Requires-Dist: einops-exts>=0.0.4; extra == 'models'
Requires-Dist: einops>=0.8.1; extra == 'models'
Requires-Dist: environs>=14.1.1; extra == 'models'
Requires-Dist: open-clip-torch>=2.32.0; extra == 'models'
Requires-Dist: sacremoses>=0.1.1; extra == 'models'
Requires-Dist: transformers>=4.49.0; extra == 'models'
